lyricli/__init__.py
lyricli/__main__.py
lyricli/console.py
lyricli/exceptions.py
lyricli/melon.py
lyricli/output.py
lyricli/parser.py
lyricli-0.0.11.dist-info/LICENSE
lyricli-0.0.11.dist-info/METADATA
lyricli-0.0.11.dist-info/WHEEL
lyricli-0.0.11.dist-info/entry_points.txt
lyricli-0.0.11.dist-info/top_level.txt
lyricli-0.0.11.dist-info/RECORD
