Metadata-Version: 2.1
Name: lyricli
Version: 0.0.11
Summary: Cli tool made with python for viewing lyrics
Home-page: https://github.com/KKodiac/lyricli
Author: Sean Hong
Author-email: seanhong2000@gmail.com
License: UNKNOWN
Project-URL: Bug Tracker, https://github.com/KKodaic/lyricli/issues
Platform: UNKNOWN
Classifier: Environment :: Console
Classifier: Programming Language :: Python
Classifier: Programming Language :: Python :: 3.7
Classifier: Programming Language :: Python :: 3.8
Classifier: Programming Language :: Python :: 3.9
Classifier: Programming Language :: Python :: 3 :: Only
Classifier: License :: OSI Approved :: MIT License
Classifier: Operating System :: OS Independent
Requires-Python: >=3.6
License-File: LICENSE
Requires-Dist: beautifulsoup4
Requires-Dist: six
Requires-Dist: lxml
Requires-Dist: requests
